listing_tracker/__init__.py
listing_tracker/__main__.py
listing_tracker/dir.py
listing_tracker/database/__init__.py
listing_tracker/database/classes.py
listing_tracker/database/connection.py
listing_tracker/database/listings.py
listing_tracker/database/websites.py
listing_tracker-0.1.0.dist-info/licenses/LICENSE.txt
listing_tracker-0.1.0.dist-info/METADATA
listing_tracker-0.1.0.dist-info/WHEEL
listing_tracker-0.1.0.dist-info/top_level.txt
listing_tracker-0.1.0.dist-info/RECORD
