Metadata-Version: 2.4
Name: listing_tracker
Version: 0.1.0
Summary: Monitor E-Commerce Webpages/Listings
Author-email: Samantha Bales <samanthabales2006@gmail.com>
Keywords: listing,e-commerce,tracking,monitoring
Classifier: Development Status :: 1 - Planning
Classifier: Programming Language :: Python
Requires-Python: >=3.10
License-File: LICENSE.txt
Dynamic: license-file
